pyatlasobscura/__init__.py
pyatlasobscura/cache.py
pyatlasobscura/client/__init__.py
pyatlasobscura/client/base.py
pyatlasobscura/client/pandas.py
pyatlasobscura/models/__init__.py
pyatlasobscura/models/base.py
pyatlasobscura/models/destinations.py
pyatlasobscura/models/query.py
pyatlasobscura/models/util.py
test/__init__.py
test/test_client.py
pyatlasobscura-0.1.1.dist-info/LICENSE
pyatlasobscura-0.1.1.dist-info/METADATA
pyatlasobscura-0.1.1.dist-info/WHEEL
pyatlasobscura-0.1.1.dist-info/top_level.txt
pyatlasobscura-0.1.1.dist-info/RECORD
